src/__init__.py
src/build.py
src/etlx.py
src/go.py
pyetlx-0.1.1.dist-info/LICENSE
pyetlx-0.1.1.dist-info/METADATA
pyetlx-0.1.1.dist-info/WHEEL
pyetlx-0.1.1.dist-info/top_level.txt
pyetlx-0.1.1.dist-info/RECORD
