Metadata-Version: 2.1
Name: pyetlx
Version: 0.1.1
Summary: Python bindings for the etlx Go library
Author-email: Real Data-Driven <real.datadriven@gmail.com>
Project-URL: Homepage, https://github.com/realdatadriven/etlx
Project-URL: Bug Tracker, https://github.com/realdatadriven/etlx/issues
Classifier: Programming Language :: Python :: 3
Classifier: License :: OSI Approved :: MIT License
Classifier: Operating System :: OS Independent
Requires-Python: >=3.6
License-File: LICENSE
